netatmo2influxdb/__init__.py
netatmo2influxdb/__main__.py
netatmo2influxdb/__version__.py
netatmo2influxdb/data.py
netatmo2influxdb/db.py
netatmo2influxdb/logger.py
netatmo2influxdb/parser.py
netatmo2influxdb/store.py
netatmo2influxdb/tokens.py
netatmo2influxdb-0.1.2.dist-info/LICENSE
netatmo2influxdb-0.1.2.dist-info/METADATA
netatmo2influxdb-0.1.2.dist-info/WHEEL
netatmo2influxdb-0.1.2.dist-info/top_level.txt
netatmo2influxdb-0.1.2.dist-info/RECORD
