Metadata-Version: 2.1
Name: netatmo2influxdb
Version: 0.1.2
Summary: Send Netatmo Thermostat data to InfluxDB.
Home-page: https://gitlab.com/zegerius/netatmo-to-influxdb
Author: Aram Zegerius
Author-email: aram@zegeri.us
License: MIT
Platform: UNKNOWN
Classifier: License :: OSI Approved :: MIT License
Classifier: Programming Language :: Python
Classifier: Programming Language :: Python :: 3
Classifier: Programming Language :: Python :: 3.7
Classifier: Programming Language :: Python :: Implementation :: CPython
Classifier: Programming Language :: Python :: Implementation :: PyPy
Requires-Python: >=3.7.0
Requires-Dist: requests
Requires-Dist: influxdb
